[
    {
        "type": "message",
        "user": "U62R1805P",
        "text": "So I got the quick install running on Ubuntu (under VMWare as it supports nested virtualization)  I added another VMWare VM set it to PXE boot, and it did...  (the node showed up in the DHCP with it's MAC and IP) but when it rebooted, the VM image seemed to have lost the network card used during the PXE boot.  The Host system still sees the IP and the route but I don't think sledgehammer can report info to DR.",
        "ts": "1500053405.722658"
    },
    {
        "type": "message",
        "subtype": "file_share",
        "text": "<@U62R1805P> uploaded a file: <https:\/\/rackn.slack.com\/files\/U62R1805P\/F696PUPQV\/screen_shot_2017-07-14_at_12.31.10_pm.png|Screen Shot 2017-07-14 at 12.31.10 PM.png> and commented: THE PXEboot machine",
        "file": {
            "id": "F696PUPQV",
            "created": 1500053526,
            "timestamp": 1500053526,
            "name": "Screen Shot 2017-07-14 at 12.31.10 PM.png",
            "title": "Screen Shot 2017-07-14 at 12.31.10 PM.png",
            "mimetype": "image\/png",
            "filetype": "png",
            "pretty_type": "PNG",
            "user": "U62R1805P",
            "editable": false,
            "size": 37530,
            "mode": "hosted",
            "is_external": false,
            "external_type": "",
            "is_public": true,
            "public_url_shared": false,
            "display_as_bot": false,
            "username": "",
            "url_private": "https:\/\/files.slack.com\/files-pri\/T02DGQYJZ-F696PUPQV\/screen_shot_2017-07-14_at_12.31.10_pm.png?t=xoxe-2458848645-331142845857-332542502102-c2a3393bdc66e7bf33d1c6986e4eea64",
            "url_private_download": "https:\/\/files.slack.com\/files-pri\/T02DGQYJZ-F696PUPQV\/download\/screen_shot_2017-07-14_at_12.31.10_pm.png?t=xoxe-2458848645-331142845857-332542502102-c2a3393bdc66e7bf33d1c6986e4eea64",
            "thumb_64": "https:\/\/files.slack.com\/files-tmb\/T02DGQYJZ-F696PUPQV-f76d270536\/screen_shot_2017-07-14_at_12.31.10_pm_64.png?t=xoxe-2458848645-331142845857-332542502102-c2a3393bdc66e7bf33d1c6986e4eea64",
            "thumb_80": "https:\/\/files.slack.com\/files-tmb\/T02DGQYJZ-F696PUPQV-f76d270536\/screen_shot_2017-07-14_at_12.31.10_pm_80.png?t=xoxe-2458848645-331142845857-332542502102-c2a3393bdc66e7bf33d1c6986e4eea64",
            "thumb_360": "https:\/\/files.slack.com\/files-tmb\/T02DGQYJZ-F696PUPQV-f76d270536\/screen_shot_2017-07-14_at_12.31.10_pm_360.png?t=xoxe-2458848645-331142845857-332542502102-c2a3393bdc66e7bf33d1c6986e4eea64",
            "thumb_360_w": 360,
            "thumb_360_h": 227,
            "thumb_480": "https:\/\/files.slack.com\/files-tmb\/T02DGQYJZ-F696PUPQV-f76d270536\/screen_shot_2017-07-14_at_12.31.10_pm_480.png?t=xoxe-2458848645-331142845857-332542502102-c2a3393bdc66e7bf33d1c6986e4eea64",
            "thumb_480_w": 480,
            "thumb_480_h": 303,
            "thumb_160": "https:\/\/files.slack.com\/files-tmb\/T02DGQYJZ-F696PUPQV-f76d270536\/screen_shot_2017-07-14_at_12.31.10_pm_160.png?t=xoxe-2458848645-331142845857-332542502102-c2a3393bdc66e7bf33d1c6986e4eea64",
            "thumb_720": "https:\/\/files.slack.com\/files-tmb\/T02DGQYJZ-F696PUPQV-f76d270536\/screen_shot_2017-07-14_at_12.31.10_pm_720.png?t=xoxe-2458848645-331142845857-332542502102-c2a3393bdc66e7bf33d1c6986e4eea64",
            "thumb_720_w": 720,
            "thumb_720_h": 454,
            "image_exif_rotation": 1,
            "original_w": 725,
            "original_h": 457,
            "permalink": "https:\/\/rackn.slack.com\/files\/U62R1805P\/F696PUPQV\/screen_shot_2017-07-14_at_12.31.10_pm.png",
            "permalink_public": "https:\/\/slack-files.com\/T02DGQYJZ-F696PUPQV-14227a8657",
            "channels": [],
            "groups": [],
            "ims": [],
            "comments_count": 1,
            "initial_comment": {
                "id": "Fc696Q03EZ",
                "created": 1500053526,
                "timestamp": 1500053526,
                "user": "U62R1805P",
                "is_intro": true,
                "comment": "THE PXEboot machine"
            }
        },
        "user": "U62R1805P",
        "upload": true,
        "display_as_bot": false,
        "username": "ctrees",
        "bot_id": null,
        "ts": "1500053528.786799"
    },
    {
        "type": "message",
        "user": "U62R1805P",
        "text": "I suspect it's a VMWare thing just wondering if you've ever seen this issue.",
        "ts": "1500053682.865400"
    },
    {
        "type": "message",
        "user": "U62R1805P",
        "text": "Tried the 'devices.hotplug = \"FALSE\" ' .vmx mod solution",
        "ts": "1500056549.323700"
    },
    {
        "type": "message",
        "user": "U62R1805P",
        "text": "<http:\/\/www.techieshelp.com\/cannot-see-vm-nic\/>",
        "attachments": [
            {
                "title": "Virtual Network card on VMWARE guest disappears",
                "title_link": "http:\/\/www.techieshelp.com\/cannot-see-vm-nic\/",
                "text": "In vmware you may find the the virtual NIC dissapears, this is a known issue, here is how to resolve the VM nic issue.",
                "fallback": "Virtual Network card on VMWARE guest disappears",
                "from_url": "http:\/\/www.techieshelp.com\/cannot-see-vm-nic\/",
                "service_icon": "http:\/\/www.techieshelp.com\/wp-content\/themes\/yoo_monday_wp\/apple_touch_icon.png",
                "service_name": "techieshelp.com",
                "id": 1
            }
        ],
        "ts": "1500056563.330573"
    },
    {
        "type": "message",
        "user": "U62R1805P",
        "text": "no happiness...",
        "ts": "1500056584.340755"
    },
    {
        "type": "message",
        "user": "U02DGQYK1",
        "text": "You need to make sure that the mac is set and not changing.  Also, the client vm should have only one NIC in one network.",
        "ts": "1500057175.644880"
    },
    {
        "type": "message",
        "user": "U62R1805P",
        "text": "Yup... I set MAC static AND only one NIC... again I'm pretty sure it's VMWare dropping the darn thing, just wondering if you've ran into it.",
        "ts": "1500057324.720560"
    },
    {
        "type": "message",
        "user": "U62R1805P",
        "text": "The only reason I'm doing the VM stuff is so the devs and ops guys can review each-others mods on an isolated system... I'm replicating the same setup in the C7000 blade center right now... I don't expect the have an issue with real metal as I've seen it work already.  The C7000 blade setup had issues with it's control plane wanting \/ defaulting to DHCP and need that to go access the VLAN stuff... all this inception stuff for isolation",
        "ts": "1500057563.835299"
    },
    {
        "type": "message",
        "user": "U62R1805P",
        "text": "So the best way to bring a whole grid down is digitalrebar\/deploy\/backup.sh then bring back up with digitalrebar\/deploy\/restore.sh",
        "ts": "1500070035.887806"
    },
    {
        "type": "message",
        "user": "U62R1805P",
        "text": "<https:\/\/github.com\/digitalrebar\/digitalrebar\/blob\/master\/deploy\/backup.sh>",
        "attachments": [
            {
                "service_name": "GitHub",
                "title": "digitalrebar\/digitalrebar",
                "title_link": "https:\/\/github.com\/digitalrebar\/digitalrebar\/blob\/master\/deploy\/backup.sh",
                "text": "digitalrebar - Digital Rebar: Open Hybrid DevOps &amp; SRE Automation Platform",
                "fallback": "GitHub: digitalrebar\/digitalrebar",
                "from_url": "https:\/\/github.com\/digitalrebar\/digitalrebar\/blob\/master\/deploy\/backup.sh",
                "thumb_url": "https:\/\/avatars5.githubusercontent.com\/u\/13814120?v=4&s=400",
                "thumb_width": 192,
                "thumb_height": 192,
                "service_icon": "https:\/\/a.slack-edge.com\/bfaba\/img\/unfurl_icons\/github.png",
                "id": 1
            }
        ],
        "ts": "1500070053.892602"
    },
    {
        "type": "message",
        "user": "U62R1805P",
        "text": "In backup.sh has a comment that I'm not following...",
        "ts": "1500070124.911920"
    },
    {
        "type": "message",
        "user": "U62R1805P",
        "text": "# This script handles getting the first 5 items, getting the third is\n# left as an exercise for the reader.\n<#C02L9P26Q|community>",
        "ts": "1500070129.913363"
    },
    {
        "type": "message",
        "user": "U62R1805P",
        "text": "it name 3 data sets, then 5 items, then mention 'the third' is left for the reader ?",
        "ts": "1500070198.931158"
    },
    {
        "type": "message",
        "user": "U02DHRR2L",
        "text": "\"The file data for Goiardi\" - we don't recover Chef information",
        "ts": "1500074321.846439"
    },
    {
        "type": "message",
        "user": "U02DHRR2L",
        "text": "but... it looks like it does in the script.  It's possible that comment is out of date",
        "ts": "1500074352.852097"
    }
]